psenti/__init__.py
psenti/helpers/__init__.py
psenti/helpers/logging_helpers.py
psenti/helpers/utilities.py
psenti/service/__init__.py
psenti/service/request.py
psenti/service/sentiment.py
psenti-1.0.0.dist-info/LICENSE
psenti-1.0.0.dist-info/METADATA
psenti-1.0.0.dist-info/WHEEL
psenti-1.0.0.dist-info/top_level.txt
psenti-1.0.0.dist-info/RECORD
