Metadata-Version: 2.1
Name: psenti
Version: 1.0.0
Summary: pSenti API
Home-page: https://github.com/AndMu/Wikiled.Sentiment.Service
Author: Wikiled
License: UNKNOWN
Platform: UNKNOWN
Classifier: Programming Language :: Python :: 3
Classifier: License :: OSI Approved :: MIT License
Classifier: Operating System :: OS Independent
Requires-Python: >3.6
Requires-Dist: requests (==2.26.0)
Requires-Dist: pathlib2 (==2.3.6)
Requires-Dist: jsonpickle (==2.0.0)
Requires-Dist: websockets (==10.0)
Requires-Dist: scikit-learn (==0.24.2)
